vxaat/__init__.py
vxaat/ussd.py
vxaat/tests/__init__.py
vxaat/tests/test_ussd.py
vxaat-0.5.6.dist-info/METADATA
vxaat-0.5.6.dist-info/RECORD
vxaat-0.5.6.dist-info/WHEEL
vxaat-0.5.6.dist-info/top_level.txt
