Metadata-Version: 2.1
Name: vxaat
Version: 0.5.6
Summary: An AAT USSD transport for Vumi.
Home-page: http://github.com/praekelt/vumi-aat
Author: Praekelt Foundation
Author-email: dev@praekeltfoundation.org
License: BSD
Platform: UNKNOWN
Classifier: Development Status :: 4 - Beta
Classifier: Intended Audience :: Developers
Classifier: License :: OSI Approved :: BSD License
Classifier: Operating System :: POSIX
Classifier: Programming Language :: Python
Classifier: Topic :: Software Development :: Libraries :: Python Modules
Classifier: Topic :: System :: Networking
Requires-Dist: vumi
Requires-Dist: Twisted (>=13.1.0)
